pyRNumerosPrimos/__init__.py
pyRNumerosPrimos-0.1.dist-info/LICENSE.txt
pyRNumerosPrimos-0.1.dist-info/METADATA
pyRNumerosPrimos-0.1.dist-info/WHEEL
pyRNumerosPrimos-0.1.dist-info/top_level.txt
pyRNumerosPrimos-0.1.dist-info/RECORD
