Metadata-Version: 2.1
Name: pyRNumerosPrimos
Version: 0.1
Summary: Sistema Administrativo de pyRNumerosPrimos
Home-page: UNKNOWN
Author: MarcH
Author-email: 
License: GPL
Keywords: ejemplo instalador paquete Production/Stable
Platform: Unix
Classifier: Development Status :: 5 - Production/Stable
Classifier: Environment :: Console
Classifier: Intended Audience :: Developers
Classifier: Topic :: Software Development :: Libraries
Classifier: License :: Freely Distributable
Classifier: Programming Language :: Python
Classifier: Programming Language :: Python :: 3.8
Classifier: Operating System :: OS Independent
